ckanext_dcor_depot-1.0.3-py3.12-nspkg.pth
ckanext/dcor_depot/__init__.py
ckanext/dcor_depot/_version.py
ckanext/dcor_depot/app_res.py
ckanext/dcor_depot/cli.py
ckanext/dcor_depot/figshare.py
ckanext/dcor_depot/figshare_dois.txt
ckanext/dcor_depot/jobs.py
ckanext/dcor_depot/plugin.py
ckanext/dcor_depot/util.py
ckanext/dcor_depot/tests/__init__.py
ckanext/dcor_depot/tests/requirements.txt
ckanext/dcor_depot/tests/test_cli.py
ckanext/dcor_depot/tests/test_jobs.py
ckanext/dcor_depot/tests/data/calibration_beads_47.rtdc
ckanext/dcor_depot/tests/data/depotize_archive_20210123.tar.gz
ckanext_dcor_depot-1.0.3.dist-info/licenses/LICENSE
ckanext_dcor_depot-1.0.3.dist-info/METADATA
ckanext_dcor_depot-1.0.3.dist-info/WHEEL
ckanext_dcor_depot-1.0.3.dist-info/entry_points.txt
ckanext_dcor_depot-1.0.3.dist-info/namespace_packages.txt
ckanext_dcor_depot-1.0.3.dist-info/top_level.txt
ckanext_dcor_depot-1.0.3.dist-info/RECORD
