Metadata-Version: 2.4
Name: ckanext-dcor_depot
Version: 1.0.3
Summary: Manages data storage for DCOR
Author: Paul Müller
Maintainer-email: Paul Müller <dev@craban.de>
License: GNU Affero General Public License v3 or later (AGPLv3+)
Project-URL: source, https://github.com/DCOR-dev/ckanext-dcor_depot
Project-URL: tracker, https://github.com/DCOR-dev/ckanext-dcor_depot/issues
Project-URL: changelog, https://github.com/DCOR-dev/ckanext-dcor_depot/blob/main/CHANGELOG
Keywords: DC,DCOR,deformability,cytometry
Classifier: Operating System :: OS Independent
Classifier: Programming Language :: Python :: 3
Classifier: Topic :: Scientific/Engineering :: Visualization
Classifier: Intended Audience :: Science/Research
Requires-Python: <4,>=3.8
License-File: LICENSE
Requires-Dist: boto3
Requires-Dist: ckan<3,>=2.10.4
Requires-Dist: click
Requires-Dist: dclab>=0.60.9
Requires-Dist: dcor_shared>=0.14.0
Requires-Dist: h5py
Requires-Dist: html2text==2019.8.11
Requires-Dist: numpy
Requires-Dist: requests
Dynamic: license-file
